{"kind":"identitytoolkit#DownloadAccountResponse","users":[{"localId":"6r9igyc2dgKYeLYhhIEexuSEzAex","createdAt":"1622213120348","lastLoginAt":"1622213120348","displayName":"User Name","passwordHash":"fakeHash:salt=fakeSaltQYhWcPPXMzYpoRyfTvg9:password=user-password","salt":"fakeSaltQYhWcPPXMzYpoRyfTvg9","passwordUpdatedAt":1626898216921,"providerUserInfo":[{"providerId":"password","email":"user@user.com","federatedId":"user@user.com","rawId":"user@user.com","displayName":"User Name"}],"validSince":"1626898216","email":"user@user.com","emailVerified":false,"disabled":false},{"localId":"B4sSGRKdoIInDFfsBfq4jc8DFpFO","createdAt":"1619184322702","lastLoginAt":"1619184322702","displayName":"Admin","photoUrl":"","passwordHash":"fakeHash:salt=fakeSalt3HlqMM8GRb7iu4LTzLnd:password=admin1","salt":"fakeSalt3HlqMM8GRb7iu4LTzLnd","passwordUpdatedAt":1626898216922,"customAttributes":"{\"admin\": true}","providerUserInfo":[{"providerId":"password","email":"admin@admin.com","federatedId":"admin@admin.com","rawId":"admin@admin.com","displayName":"Admin","photoUrl":""}],"validSince":"1626898216","email":"admin@admin.com","emailVerified":false,"disabled":false},{"localId":"zSc1GJ30ZfTfHOLm6PEP0ilZO1ax","createdAt":"1622222773711","lastLoginAt":"1622222773711","displayName":"First Last","passwordHash":"fakeHash:salt=fakeSaltfARtzLJvgBFbvUUhZ9sw:password=user-password","salt":"fakeSaltfARtzLJvgBFbvUUhZ9sw","passwordUpdatedAt":1626898216922,"providerUserInfo":[{"providerId":"password","email":"user1@user.com","federatedId":"user1@user.com","rawId":"user1@user.com","displayName":"First Last"}],"validSince":"1626898216","email":"user1@user.com","emailVerified":false,"disabled":false}]}